idum_proxy/__init__.py
idum_proxy/async_logger.py
idum_proxy/default.json
idum_proxy/idum_proxy.py
idum_proxy/py.typed
idum_proxy/config/__init__.py
idum_proxy/config/loader.py
idum_proxy/config/models.py
idum_proxy/files/__init__.py
idum_proxy/files/reader/__init__.py
idum_proxy/files/reader/io_async_reader.py
idum_proxy/middlewares/__init__.py
idum_proxy/middlewares/content_length_middleware.py
idum_proxy/middlewares/performance/__init__.py
idum_proxy/middlewares/performance/circuit_breaker.py
idum_proxy/middlewares/performance/compression.py
idum_proxy/middlewares/performance/resource_filter.py
idum_proxy/middlewares/performance/caching/__init__.py
idum_proxy/middlewares/performance/caching/in_file.py
idum_proxy/middlewares/performance/caching/in_memory.py
idum_proxy/middlewares/security/__init__.py
idum_proxy/middlewares/security/bot_filter.py
idum_proxy/middlewares/security/ip_filter.py
idum_proxy/middlewares/transformer/__init__.py
idum_proxy/middlewares/transformer/request_transform.py
idum_proxy/middlewares/transformer/response_transform.py
idum_proxy/networking/__init__.py
idum_proxy/networking/connection_pooling/__init__.py
idum_proxy/networking/connection_pooling/connection_pooling.py
idum_proxy/networking/load_balancing/__init__.py
idum_proxy/networking/routing/__init__.py
idum_proxy/networking/routing/routing_selector.py
idum_proxy/protocols/__init__.py
idum_proxy/protocols/https.py
idum_proxy/protocols/socks.py
idum_proxy/protocols/tcp.py
idum_proxy/protocols/tls.py
idum_proxy/protocols/udp.py
idum_proxy/protocols/websocket.py
idum_proxy/security/__init__.py
idum_proxy/security/authentication/__init__.py
idum_proxy/security/authentication/auth.py
idum_proxy/security/authentication/basic_auth.py
idum_proxy/security/authentication/jwt_auth.py
idum_proxy/security/authorization/__init__.py
idum_proxy/upstreams/__init__.py
idum_proxy/upstreams/backends/__init__.py
idum_proxy/upstreams/backends/file_system/__init__.py
idum_proxy-1.1.2.dist-info/METADATA
idum_proxy-1.1.2.dist-info/WHEEL
idum_proxy-1.1.2.dist-info/entry_points.txt
idum_proxy-1.1.2.dist-info/licenses/LICENSE
idum_proxy-1.1.2.dist-info/RECORD
