Metadata-Version: 2.4
Name: idum_proxy
Version: 1.1.2
Summary: ⚡ High-performance Python proxy server with authentication, load balancing, caching, and multi-protocol support
Project-URL: homepage, https://github.com/idumhq/idum-proxy
Project-URL: documentation, https://github.com/idumhq/idum-proxy
Project-URL: repository, https://github.com/idumhq/idum-proxy
Project-URL: changelog, https://github.com/idumhq/idum-proxy/releases
Author-email: Sylvain Mouquet <sylvain.mouquet@gmail.com>
License: MIT
License-File: LICENSE
Keywords: authentication,http,https,load-balancing,networking,proxy,python,reverse-proxy,socks5,websocket
Classifier: Development Status :: 5 - Production/Stable
Classifier: Framework :: Pytest
Classifier: Intended Audience :: Developers
Classifier: License :: OSI Approved :: MIT License
Classifier: Programming Language :: Python
Classifier: Programming Language :: Python :: 3
Classifier: Programming Language :: Python :: 3.13
Classifier: Topic :: Software Development :: Libraries :: Python Modules
Requires-Python: >=3.13
Requires-Dist: aiofile>=3.9.0
Requires-Dist: aiofiles>=24.1.0
Requires-Dist: aiohttp>=3.11.18
Requires-Dist: antpathmatcher>=1.0.0
Requires-Dist: apscheduler>=3.11.0
Requires-Dist: gunicorn>=23.0.0
Requires-Dist: httpx>=0.28.1
Requires-Dist: pydantic>=2.11.4
Requires-Dist: python-jose>=3.4.0
Requires-Dist: starlette>=0.46.2
Requires-Dist: structlog>=25.3.0
Requires-Dist: uvicorn>=0.34.2
